call_graph.py
fuzzycallgraph-0.0.3.dist-info/METADATA
fuzzycallgraph-0.0.3.dist-info/RECORD
fuzzycallgraph-0.0.3.dist-info/WHEEL
fuzzycallgraph-0.0.3.dist-info/entry_points.txt
fuzzycallgraph-0.0.3.dist-info/top_level.txt
