Metadata-Version: 2.1
Name: fuzzycallgraph
Version: 0.0.3
Summary: Fuzzy call graphs
Home-page: https://github.com/d-babiak/fuzzy-call-graph
Author: dmb
Author-email: d.babiak@gmail.com
License: MIT
Platform: UNKNOWN
Classifier: License :: OSI Approved :: MIT License
Classifier: Programming Language :: Python
Classifier: Programming Language :: Python :: 3
Classifier: Programming Language :: Python :: 3.6
Classifier: Programming Language :: Python :: Implementation :: CPython
Classifier: Programming Language :: Python :: Implementation :: PyPy
Requires-Python: >=3.6.0
